furniture/__init__.py
furniture/animation.py
furniture/geometry.py
furniture/text.py
furniture_typo-0.0.1.dist-info/LICENSE
furniture_typo-0.0.1.dist-info/METADATA
furniture_typo-0.0.1.dist-info/WHEEL
furniture_typo-0.0.1.dist-info/top_level.txt
furniture_typo-0.0.1.dist-info/RECORD
